kaededb/__init__.py
kaededb_server/__init__.py
kaededb_server/api.py
kaededb_server/kdb_core.py
kaededb_server/setup.py
kaededb-9.dist-info/METADATA
kaededb-9.dist-info/WHEEL
kaededb-9.dist-info/top_level.txt
kaededb-9.dist-info/RECORD
